src/__init__.py
src/__main__.py
src/ui_mainwindow.py
src/utils.py
src/viewer.py
quadcropper-0.4.dist-info/LICENSE
quadcropper-0.4.dist-info/METADATA
quadcropper-0.4.dist-info/WHEEL
quadcropper-0.4.dist-info/entry_points.txt
quadcropper-0.4.dist-info/top_level.txt
quadcropper-0.4.dist-info/RECORD
